guiElements/__init__.py
guiElements/inputs/__init__.py
guiElements/inputs/button.py
guiElements/inputs/color_picker.py
guiElements/inputs/drop_down_menu.py
guiElements/inputs/label.py
guiElements/inputs/text_input.py
guiElements/window/__init__.py
guiElements/window/window.py
guiElements/window/window_events.py
guiElements-0.0.6.dist-info/LICENSE.txt
guiElements-0.0.6.dist-info/METADATA
guiElements-0.0.6.dist-info/WHEEL
guiElements-0.0.6.dist-info/top_level.txt
guiElements-0.0.6.dist-info/RECORD
