Metadata-Version: 2.1
Name: guiElements
Version: 0.0.6
Summary: Make pygame apps easier
Home-page: https://github.com/ricardo-quintela/guiElements
Author: ricardoquinteladev
Author-email: 
Classifier: Programming Language :: Python :: 3
Classifier: License :: OSI Approved :: MIT License
Classifier: Operating System :: OS Independent
Requires-Python: >=3.7
License-File: LICENSE.txt
